setup.cfg
setup.py
tastypie_celery_resource/__init__.py
tastypie_celery_resource/resource.py
tastypie_celery_resource.egg-info/PKG-INFO
tastypie_celery_resource.egg-info/SOURCES.txt
tastypie_celery_resource.egg-info/dependency_links.txt
tastypie_celery_resource.egg-info/requires.txt
tastypie_celery_resource.egg-info/top_level.txt
tests/__init__.py
tests/test_resource.py
tests/test_settings.py
tests/test_urls.py