Metadata-Version: 1.1
Name: tastypie-celery-resource
Version: 0.0.3
Summary: Tastypie Resource - representation of Celery Task
Home-page: http://bitbucket.org/maho/tastypie_celery_resource
Author: Maho
Author-email: maho@pagema.net
License: GPL
Download-URL: https://bitbucket.org/maho/tastypie_celery_resource/get/0.0.3.tar.bz2
Keywords: tastypie,celery
Platform: UNKNOWN
